{
  "version": "7",
  "dialect": "sqlite",
  "entries": [
    {
      "idx": 0,
      "version": "6",
      "when": 1752767974426,
      "tag": "0000_flat_tyger_tiger",
      "breakpoints": true
    },
    {
      "idx": 1,
      "version": "6",
      "when": 1752941490463,
      "tag": "0001_gifted_nightcrawler",
      "breakpoints": true
    },
    {
      "idx": 2,
      "version": "6",
      "when": 1753099500333,
      "tag": "0002_demonic_shinko_yamashiro",
      "breakpoints": true
    },
    {
      "idx": 3,
      "version": "6",
      "when": 1753264922980,
      "tag": "0003_chief_mystique",
      "breakpoints": true
    },
    {
      "idx": 4,
      "version": "6",
      "when": 1753265529388,
      "tag": "0004_small_supernaut",
      "breakpoints": true
    },
    {
      "idx": 5,
      "version": "6",
      "when": 1743264000000,
      "tag": "0005_company_split_identifiers",
      "breakpoints": true
    },
    {
      "idx": 6,
      "version": "6",
      "when": 1775296922085,
      "tag": "0006_dazzling_sharon_ventura",
      "breakpoints": true
    },
    {
      "idx": 7,
      "version": "6",
      "when": 1775383322085,
      "tag": "0007_stamp_table",
      "breakpoints": true
    },
    {
      "idx": 8,
      "version": "6",
      "when": 1782047970658,
      "tag": "0008_my_company",
      "breakpoints": true
    },
    {
      "idx": 9,
      "version": "6",
      "when": 1782048070658,
      "tag": "0009_rename_item_prices",
      "breakpoints": true
    }
  ]
}